{
  "name": "书香墨韵",
  "preview": {
    "description": "经典阅读体验，适合长文深度阅读",
    "features": ["黑白简约", "大字号", "荧光强调"]
  },
  "config": {
    "title": {
      "show": true,
      "editable": true,
      "fontSize": "26px",
      "fontFamily": "-apple-system, BlinkMacSystemFont, 'PingFang SC', 'Hiragino Sans GB', 'Microsoft YaHei', sans-serif",
      "fontWeight": "800",
      "color": "#1a1a1a",
      "textAlign": "center",
      "marginBottom": "2rem",
      "borderTop": "3px solid #1a1a1a",
      "borderBottom": "3px solid #1a1a1a",
      "padding": "18px 0",
      "letterSpacing": "3px"
    },
    "content": {
      "show": true,
      "editable": true,
      "fontSize": "18px",
      "fontFamily": "-apple-system, BlinkMacSystemFont, 'PingFang SC', 'Hiragino Sans GB', 'Microsoft YaHei', sans-serif",
      "color": "#2a2a2a",
      "textAlign": "justify",
      "lineHeight": "1.95",
      "maxCharsPerLine": 22,
      "backgroundColor": "#f8f8f8",
      "backdropFilter": "none",
      "padding": "48px",
      "borderRadius": "6px"
    },
    "author": {
      "show": true,
      "editable": true,
      "position": "bottom-left",
      "avatarSize": "40px",
      "nicknameSize": "14px",
      "nicknameColor": "#1a1a1a",
      "usernameSize": "10px",
      "usernameColor": "#404040",
      "allowCustomAvatar": true,
      "allowSocialIcon": true
    },
    "time": {
      "show": true,
      "editable": true,
      "position": "with-author",
      "format": "YYYY-MM-DD",
      "fontSize": "10px",
      "color": "#888"
    },
    "pageNumber": {
      "show": true,
      "editable": true,
      "position": "bottom-right",
      "format": "number",
      "fontSize": "10px",
      "color": "#1a1a1a"
    },
    "watermark": {
      "show": true,
      "editable": true,
      "position": "bottom-right",
      "text": "书香墨韵",
      "fontSize": "10px",
      "color": "#999",
      "opacity": 0.5
    },
    "canvas": {
      "background": "#ffffff",
      "padding": 48,
      "borderRadius": 0,
      "bgType": "light"
    },
    "markdown": {
      "h2": {
        "fontSize": "20px",
        "padding": "0.3em 1em",
        "borderRadius": "30px",
        "boxShadow": "0 4px 6px rgba(0, 0, 0, 0.1)"
      },
      "h3": {
        "fontSize": "18px",
        "borderLeft": "5px solid #1a1a1a",
        "paddingLeft": "20px",
        "background": "linear-gradient(to right, rgba(26, 26, 26, 0.04), transparent 50%)"
      },
      "strong": {
        "background": "linear-gradient(to bottom, transparent 65%, rgba(255, 235, 59, 0.7) 65%)",
        "color": "#1a1a1a"
      },
      "blockquote": {
        "background": "#f8f8f8",
        "borderLeft": "5px solid #eee",
        "color": "#888"
      }
    }
  }
}
